CHANGELOG.md
CMakeLists.txt
CONTRIBUTORS.md
LICENSE.txt
MANIFEST.in
README.md
asgard-config.cmake
asgard-env.sh
pyproject.toml
setup.py
contrib/FindASGARDLINALG.cmake
contrib/asgard_io.cmake
doxygen/CMakeLists.txt
doxygen/MPI.md
doxygen/asgard.css
doxygen/basic_usage.md
doxygen/footer.html
doxygen/header.html
doxygen/installation.md
doxygen/plotting.md
examples/CMakeLists.txt
examples/continuity_2d.cpp
examples/continuity_2d.m
examples/continuity_2d.py
examples/inputs_1d.cpp
examples/inputs_1d.py
examples/inputs_1d_1.txt
examples/inputs_1d_2.txt
examples/slideshow.py
infiles/continuity2dsg.txt
infiles/landau1x3vasg.txt
infiles/riemann1x3vmg.txt
infiles/twostream2dasg.txt
ornl_asgard.egg-info/PKG-INFO
ornl_asgard.egg-info/SOURCES.txt
ornl_asgard.egg-info/dependency_links.txt
ornl_asgard.egg-info/requires.txt
ornl_asgard.egg-info/top_level.txt
python/asgard.py
python/asgard_cell_centers.m
python/asgard_config.py
python/asgard_evaluate.m
python/asgard_file_stats.m
python/asgard_matlab.py
python/asgard_plot1d.m
python/asgard_plot2d.m
python/asgardplot.sh
python/asgardrun.sh
python/pyasgard_test.py
python/sandbox.py
python/pipinstall/MANIFEST.in
python/pipinstall/make_tarball.sh
python/pipinstall/pyproject.toml
python/pipinstall/setup.py
src/asgard.h
src/asgard.hpp
src/asgard_blas.hpp
src/asgard_block_matrix.cpp
src/asgard_block_matrix.hpp
src/asgard_build_info.hpp.in
src/asgard_coefficients_mats.hpp
src/asgard_coefficients_mats_tests.cpp
src/asgard_compute.cpp
src/asgard_compute.hpp
src/asgard_compute_cpu.hpp
src/asgard_compute_cuda.hpp
src/asgard_compute_rocm.hpp
src/asgard_compute_tests.cpp
src/asgard_discretization.cpp
src/asgard_discretization.hpp
src/asgard_discretization_tests.cpp
src/asgard_domain.hpp
src/asgard_gpu_algorithms.hpp
src/asgard_gpu_algorithms_cuda.cpp
src/asgard_gpu_algorithms_rocm.cpp
src/asgard_grid_1d.cpp
src/asgard_grid_1d.hpp
src/asgard_indexset.cpp
src/asgard_indexset.hpp
src/asgard_indexset_tests.cpp
src/asgard_interp.cpp
src/asgard_interp.hpp
src/asgard_interp_tests.cpp
src/asgard_io.cpp
src/asgard_io.hpp
src/asgard_io_tests.cpp
src/asgard_kronmult.hpp
src/asgard_kronmult_cpu.cpp
src/asgard_kronmult_cuda.cpp
