Metadata-Version: 2.2
Name: ornl-asgard
Version: 0.9.0b1
Summary: Library for high-dimensional PDEs using sparse grids and discontinuous Galerkin method
Home-page: https://github.com/project-asgard/asgard
Author: Miroslav Stoyanov
Author-email: stoyanovmk@ornl.gov
License: MIT
Classifier: Programming Language :: Python :: 3
Classifier: Programming Language :: C++
Classifier: Development Status :: 3 - Alpha
Classifier: Operating System :: OS Independent
Classifier: Operating System :: MacOS
Classifier: Operating System :: POSIX :: Linux
Classifier: Topic :: Scientific/Engineering :: Mathematics
License-File: LICENSE.txt
Requires-Dist: numpy>=1.10
Requires-Dist: h5py>=3.6
Requires-Dist: scipy>=1.8
Requires-Dist: matplotlib>=3.5
Dynamic: author
Dynamic: author-email
Dynamic: description
Dynamic: description-content-type
Dynamic: home-page
Dynamic: requires-dist
Dynamic: summary
